code_hammer/__init__.py
code_hammer/core/__init__.py
code_hammer/core/cli.py
code_hammer/core/main.py
code_hammer/core/prompt.py
codehammer/__init__.py
codehammer/core/__init__.py
codehammer/core/cli.py
codehammer/core/main.py
codehammer/core/prompt.py
codehammer-0.0.1.dist-info/METADATA
codehammer-0.0.1.dist-info/WHEEL
codehammer-0.0.1.dist-info/entry_points.txt
codehammer-0.0.1.dist-info/top_level.txt
codehammer-0.0.1.dist-info/RECORD
