Metadata-Version: 2.2
Name: codehammer
Version: 0.0.1
Summary: A tool to combine code files into a single prompt
Home-page: https://github.com/RobinsonGarcia/CodeHammer
Author: RG
Author-email: rlsgarcia@icloud.com
Classifier: Programming Language :: Python :: 3
Classifier: License :: OSI Approved :: MIT License
Classifier: Operating System :: OS Independent
Requires-Python: >=3.7
Requires-Dist: pytest
Requires-Dist: pydantic
Requires-Dist: langchain
Requires-Dist: pathspec
Requires-Dist: langchain_community
Dynamic: author
Dynamic: author-email
Dynamic: classifier
Dynamic: description
Dynamic: description-content-type
Dynamic: home-page
Dynamic: requires-dist
Dynamic: requires-python
Dynamic: summary
